{"quote":[{"securityType":"Common Stock","symbol":"TGI","exchange":"Bursa Malays","country":"Malaysia","currency":"MYR","resourceType":"Company","fundamentalDataCurrency":"MYR","resourceSubtype":"Other","region":"APAC","ticker":"tgi:mk","tickerName":"TGI:MK","template":"Stock","tinyName":"Thong Guan Industries Bhd","name":"Thong Guan Industries Bhd","watchlist":true,"resourceId":"TGI:MK","id":"TGI:MK","title":"Thong Guan Industries Bhd","card":"security"},{"securityType":"Common Stock","symbol":"TGI","exchange":"New York","country":"United States","currency":"USD","resourceType":"Company","fundamentalDataCurrency":"USD","resourceSubtype":"Other","region":"AMERICAS","ticker":"tgi:us","tickerName":"TGI:US","template":"Stock","tinyName":"Triumph Group Inc","name":"Triumph Group Inc","watchlist":true,"resourceId":"TGI:US","id":"TGI:US","title":"Triumph Group Inc","card":"security"},{"securityType":"Common Stock","symbol":"TGIF","exchange":"Canadian Sec","country":"Canada","currency":"CAD","resourceType":"Company","fundamentalDataCurrency":"CAD","resourceSubtype":"Other","region":"AMERICAS","ticker":"tgif:cn","tickerName":"TGIF:CN","template":"Stock","tinyName":"1933 Industries Inc","name":"1933 Industries Inc","watchlist":true,"resourceId":"TGIF:CN","id":"TGIF:CN","title":"1933 Industries Inc","card":"security"},{"securityType":"Common Stock","symbol":"TGI","exchange":"Tel Aviv","country":"Israel","currency":"ILs","resourceType":"Company","fundamentalDataCurrency":"USD","resourceSubtype":"Other","region":"EMEA","ticker":"tgi:it","tickerName":"TGI:IT","template":"Stock","tinyName":"TGI Infrastructures Ltd","name":"TGI Infrastructures Ltd","watchlist":true,"resourceId":"TGI:IT","id":"TGI:IT","title":"TGI Infrastructures Ltd","card":"security"},{"securityType":"Common Stock","symbol":"TGI","exchange":"Frankfurt","country":"United States","currency":"EUR","resourceType":"Company","fundamentalDataCurrency":"USD","resourceSubtype":"Other","region":"EMEA","ticker":"tgi:gr","tickerName":"TGI:GR","template":"Stock","tinyName":"TETRA Technologies Inc","name":"TETRA Technologies Inc","watchlist":true,"resourceId":"TGI:GR","id":"TGI:GR","title":"TETRA Technologies Inc","card":"security"},{"securityType":"Open-End Fund","symbol":"TGIFOIN","country":"United Kingdom","currency":"GBp","resourceType":"Fund","resourceSubtype":"OpenEnd","region":"EMEA","ticker":"tgifoin:ln","tickerName":"TGIFOIN:LN","template":"Mutual Fund","tinyName":"Trojan Global Income Fund","name":"Trojan Global Income Fund","watchlist":true,"resourceId":"TGIFOIN:LN","id":"TGIFOIN:LN","title":"Trojan Global Income Fund","card":"security"},{"securityType":"Open-End Fund","symbol":"TGINACE","country":"Luxembourg","currency":"EUR","resourceType":"Fund","resourceSubtype":"OpenEnd","region":"EMEA","ticker":"tginace:lx","tickerName":"TGINACE:LX","template":"Mutual Fund","tinyName":"Franklin Templeton Investment Funds - Templeton Global Income Fund","name":"Franklin Templeton Investment Funds - Templeton Global Income Fund","watchlist":true,"resourceId":"TGINACE:LX","id":"TGINACE:LX","title":"Franklin Templeton Investment Funds - Templeton Global Income Fund","card":"security"},{"securityType":"Common Stock","symbol":"TSPG","exchange":"OTC US","country":"United States","currency":"USD","resourceType":"Company","fundamentalDataCurrency":"USD","resourceSubtype":"Other","region":"AMERICAS","ticker":"tspg:us","tickerName":"TSPG:US","template":"Stock","tinyName":"TGI Solar Power Group Inc","name":"TGI Solar Power Group Inc","watchlist":true,"resourceId":"TSPG:US","id":"TSPG:US","title":"TGI Solar Power Group Inc","card":"security"},{"securityType":"Open-End Fund","symbol":"TGIFSAC","country":"United Kingdom","currency":"GBp","resourceType":"Fund","resourceSubtype":"OpenEnd","region":"EMEA","ticker":"tgifsac:ln","tickerName":"TGIFSAC:LN","template":"Mutual Fund","tinyName":"Trojan Global Income Fund","name":"Trojan Global Income Fund","watchlist":true,"resourceId":"TGIFSAC:LN","id":"TGIFSAC:LN","title":"Trojan Global Income Fund","card":"security"},{"securityType":"Fund of Funds","symbol":"TGINCPR","country":"Thailand","currency":"THB","resourceType":"Fund","resourceSubtype":"Other","region":"APAC","ticker":"tgincpr:tb","tickerName":"TGINCPR:TB","template":"Mutual Fund","tinyName":"TISCO Global Income Plus Fund","name":"TISCO Global Income Plus Fund","watchlist":true,"resourceId":"TGINCPR:TB","id":"TGINCPR:TB","title":"TISCO Global Income Plus Fund","card":"security"},{"securityType":"Open-End Fund","symbol":"TGINX","exchange":"NASDAQ GM","country":"United States","currency":"USD","resourceType":"Fund","resourceSubtype":"OpenEnd","region":"AMERICAS","ticker":"tginx:us","tickerName":"TGINX:US","template":"Mutual Fund","tinyName":"TCW Emerging Markets Income Fund","name":"TCW Emerging Markets Income Fund","watchlist":true,"resourceId":"TGINX:US","id":"TGINX:US","title":"TCW Emerging Markets Income Fund","card":"security"},{"securityType":"Open-End Fund","symbol":"TGINZAU","country":"Luxembourg","currency":"USD","resourceType":"Fund","resourceSubtype":"OpenEnd","region":"EMEA","ticker":"tginzau:lx","tickerName":"TGINZAU:LX","template":"Mutual Fund","tinyName":"Franklin Templeton Investment Funds - Templeton Global Income Fund","name":"Franklin Templeton Investment Funds - Templeton Global Income Fund","watchlist":true,"resourceId":"TGINZAU:LX","id":"TGINZAU:LX","title":"Franklin Templeton Investment Funds - Templeton Global Income Fund","card":"security"},{"securityType":"Open-End Fund","symbol":"TGIHX","exchange":"NASDAQ GM","country":"United States","currency":"USD","resourceType":"Fund","resourceSubtype":"OpenEnd","region":"AMERICAS","ticker":"tgihx:us","tickerName":"TGIHX:US","template":"Mutual Fund","tinyName":"TIAA-CREF Growth & Income Fund","name":"TIAA-CREF Growth & Income Fund","watchlist":true,"resourceId":"TGIHX:US","id":"TGIHX:US","title":"TIAA-CREF Growth & Income Fund","card":"security"},{"securityType":"Common Stock","symbol":"TGII","exchange":"Canadian Sec","country":"Canada","currency":"CAD","resourceType":"Company","fundamentalDataCurrency":"CAD","resourceSubtype":"Other","region":"AMERICAS","ticker":"tgii:cn","tickerName":"TGII:CN","template":"Stock","tinyName":"Trojan Gold Inc","name":"Trojan Gold Inc","watchlist":true,"resourceId":"TGII:CN","id":"TGII:CN","title":"Trojan Gold Inc","card":"security"},{"securityType":"Open-End Fund","symbol":"TGIIFIM","country":"Brazil","currency":"BRL","resourceType":"Fund","resourceSubtype":"OpenEnd","region":"AMERICAS","ticker":"tgiifim:bz","tickerName":"TGIIFIM:BZ","template":"Mutual Fund","tinyName":"Tg II FIM IE","name":"Tg II FIM IE","watchlist":true,"resourceId":"TGIIFIM:BZ","id":"TGIIFIM:BZ","title":"Tg II FIM IE","card":"security"},{"securityType":"Open-End Fund","symbol":"TGINAEH","country":"Luxembourg","currency":"EUR","resourceType":"Fund","resourceSubtype":"OpenEnd","region":"EMEA","ticker":"tginaeh:lx","tickerName":"TGINAEH:LX","template":"Mutual Fund","tinyName":"Franklin Templeton Investment Funds - Templeton Global Income Fund","name":"Franklin Templeton Investment Funds - Templeton Global Income Fund","watchlist":true,"resourceId":"TGINAEH:LX","id":"TGINAEH:LX","title":"Franklin Templeton Investment Funds - Templeton Global Income Fund","card":"security"},{"securityType":"Open-End Fund","symbol":"TGINBDI","country":"Luxembourg","currency":"USD","resourceType":"Fund","resourceSubtype":"OpenEnd","region":"EMEA","ticker":"tginbdi:lx","tickerName":"TGINBDI:LX","template":"Mutual Fund","tinyName":"Franklin Templeton Investment Funds - Templeton Global Income Fund","name":"Franklin Templeton Investment Funds - Templeton Global Income Fund","watchlist":true,"resourceId":"TGINBDI:LX","id":"TGINBDI:LX","title":"Franklin Templeton Investment Funds - Templeton Global Income Fund","card":"security"},{"securityType":"Fund of Funds","symbol":"TGINCPA","country":"Thailand","currency":"THB","resourceType":"Fund","resourceSubtype":"Other","region":"APAC","ticker":"tgincpa:tb","tickerName":"TGINCPA:TB","template":"Mutual Fund","tinyName":"TISCO Global Income Plus Fund","name":"TISCO Global Income Plus Fund","watchlist":true,"resourceId":"TGINCPA:TB","id":"TGINCPA:TB","title":"TISCO Global Income Plus Fund","card":"security"},{"securityType":"Open-End Fund","symbol":"TGIPKJDE","country":"Canada","currency":"CAD","resourceType":"Fund","resourceSubtype":"OpenEnd","region":"AMERICAS","ticker":"tgipkjde:cn","tickerName":"TGIPKJDE:CN","template":"Mutual Fund","tinyName":"Invesco Canadian Short-Term Bond Fund","name":"Invesco Canadian Short-Term Bond Fund","watchlist":true,"resourceId":"TGIPKJDE:CN","id":"TGIPKJDE:CN","title":"Invesco Canadian Short-Term Bond Fund","card":"security"},{"securityType":"Open-End Fund","symbol":"TGIAEH1","country":"Luxembourg","currency":"EUR","resourceType":"Fund","resourceSubtype":"OpenEnd","region":"EMEA","ticker":"tgiaeh1:lx","tickerName":"TGIAEH1:LX","template":"Mutual Fund","tinyName":"Franklin Templeton Investment Funds - Templeton Global Income Fund","name":"Franklin Templeton Investment Funds - Templeton Global Income Fund","watchlist":true,"resourceId":"TGIAEH1:LX","id":"TGIAEH1:LX","title":"Franklin Templeton Investment Funds - Templeton Global Income Fund","card":"security"},{"securityType":"Open-End Fund","symbol":"TGIAMDS","country":"Luxembourg","currency":"SGD","resourceType":"Fund","resourceSubtype":"OpenEnd","region":"EMEA","ticker":"tgiamds:lx","tickerName":"TGIAMDS:LX","template":"Mutual Fund","tinyName":"Franklin Templeton Investment Funds - Templeton Global Income Fund","name":"Franklin Templeton Investment Funds - Templeton Global Income Fund","watchlist":true,"resourceId":"TGIAMDS:LX","id":"TGIAMDS:LX","title":"Franklin Templeton Investment Funds - Templeton Global Income Fund","card":"security"},{"securityType":"Open-End Fund","symbol":"TGICANH","country":"Luxembourg","currency":"NOK","resourceType":"Fund","resourceSubtype":"OpenEnd","region":"EMEA","ticker":"tgicanh:lx","tickerName":"TGICANH:LX","template":"Mutual Fund","tinyName":"Threadneedle Lux - Global Investment Grade Credit Opportunities","name":"Threadneedle Lux - Global Investment Grade Credit Opportunities","watchlist":true,"resourceId":"TGICANH:LX","id":"TGICANH:LX","title":"Threadneedle Lux - Global Investment Grade Credit Opportunities","card":"security"},{"securityType":"Common Stock","symbol":"TGIFF","exchange":"OTC US","country":"Canada","currency":"USD","resourceType":"Company","fundamentalDataCurrency":"CAD","resourceSubtype":"Other","region":"AMERICAS","ticker":"tgiff:us","tickerName":"TGIFF:US","template":"Stock","tinyName":"1933 Industries Inc","name":"1933 Industries Inc","watchlist":true,"resourceId":"TGIFF:US","id":"TGIFF:US","title":"1933 Industries Inc","card":"security"},{"securityType":"Open-End Fund","symbol":"TGIFIAC","country":"United Kingdom","currency":"GBp","resourceType":"Fund","resourceSubtype":"OpenEnd","region":"EMEA","ticker":"tgifiac:ln","tickerName":"TGIFIAC:LN","template":"Mutual Fund","tinyName":"Trojan Global Income Fund","name":"Trojan Global Income Fund","watchlist":true,"resourceId":"TGIFIAC:LN","id":"TGIFIAC:LN","title":"Trojan Global Income Fund","card":"security"},{"securityType":"Open-End Fund","symbol":"TGIFIIN","country":"United Kingdom","currency":"GBp","resourceType":"Fund","resourceSubtype":"OpenEnd","region":"EMEA","ticker":"tgifiin:ln","tickerName":"TGIFIIN:LN","template":"Mutual Fund","tinyName":"Trojan Global Income Fund","name":"Trojan Global Income Fund","watchlist":true,"resourceId":"TGIFIIN:LN","id":"TGIFIIN:LN","title":"Trojan Global Income Fund","card":"security"}],"news":[{"title":"Middle East KFC Operator Said to Pick Banks for Dual Listing","id":"RAY8D6DWX2PT01","card":"article","date":1651051630,"longURL":"https://www.bloomberg.com/news/articles/2022-04-27/middle-east-kfc-operator-said-to-pick-banks-for-dual-listing"},{"title":"Middle East KFC Operator Said to Start Early Talks Over Listing","id":"R939RPT0G1L001","card":"article","date":1648011367,"longURL":"https://www.bloomberg.com/news/articles/2022-03-23/middle-east-kfc-operator-said-to-start-early-talks-over-listing"},{"title":"Nickel's Blowup Is Just the Start of the Market Wildness","id":"R8I0WWT0G1KY01","card":"article","date":1646864672,"longURL":"https://www.bloomberg.com/opinion/articles/2022-03-09/nickel-s-blowup-is-just-the-start-of-the-market-wildness"},{"title":"Beyond Meat Loses Some Early Fans, Stirring Worry Over Category","id":"R6DMVIDWX2QJ01","card":"article","date":1643905135,"longURL":"https://www.bloomberg.com/news/articles/2022-02-03/some-beyond-meat-early-adopters-move-on-as-others-double-down"},{"title":"TGI Friday’s Dangles $2,500 Vacation Reimbursement to Keep Staff","id":"R6C15MDWRGG001","card":"article","date":1643301884,"longURL":"https://www.bloomberg.com/news/articles/2022-01-27/tgi-friday-s-dangles-2-500-vacation-reimbursement-to-keep-staff"},{"title":"Employment Slump Pressures Consumer Companies","id":"O1OLXC6S972E01","card":"article","date":1258586799,"longURL":"https://www.bloomberg.com/news/articles/2009-11-18/employment-slump-pressures-consumer-companies"},{"title":"Curt Carlson Keeps It All In The Family","id":"NXDCX16KLVR801","card":"article","date":686203200,"longURL":"https://www.bloomberg.com/news/articles/1991-09-29/curt-carlson-keeps-it-all-in-the-family"},{"title":"NOT SO HEALTHY CHOICES","id":"O1U3W86JTSE901","card":"article","date":1173758400,"longURL":"https://www.bloomberg.com/news/articles/2007-03-12/not-so-healthy-choices"},{"title":"Cigna Slashes Forecasts, Shares Plunge","id":"O1S8QH6KLVR401","card":"article","date":1035518400,"longURL":"https://www.bloomberg.com/news/articles/2002-10-24/cigna-slashes-forecasts-shares-plunge"},{"title":"Staples Says Results Are on Track","id":"O1R1V46S972901","card":"article","date":998366400,"longURL":"https://www.bloomberg.com/news/articles/2001-08-20/staples-says-results-are-on-track"},{"title":"Midtown Manhattan Development Site to Be New Homes for Seniors","id":"O5W62Q6KLVR401","card":"article","date":1461091978,"longURL":"https://www.bloomberg.com/news/articles/2016-04-19/midtown-manhattan-development-site-to-be-new-homes-for-seniors"},{"title":"U.S. Companies Reporting Higher Quarterly EPS, May 3","id":"M3GUR21A74E901","card":"article","date":1336081070,"longURL":"https://www.bloomberg.com/news/articles/2012-05-03/u-s-companies-reporting-higher-quarterly-eps-may-3"},{"title":"U.S. Companies Reporting Positive EPS Surprises, May 3","id":"M3GUR20D9L3501","card":"article","date":1336081070,"longURL":"https://www.bloomberg.com/news/articles/2012-05-03/u-s-companies-reporting-positive-eps-surprises-may-3"},{"title":"Major Snowstorm Disrupts Travel, Shopping in Northeast U.S.","id":"KUWM9S0UQVI901","card":"article","date":1261285260,"longURL":"https://www.bloomberg.com/news/articles/2009-12-19/major-snowstorm-threatens-blizzard-for-u-s-northeast"},{"title":"Fatal Flying on Airlines No Accident in Pilot Complaints to FAA","id":"KVFTVX0UQVI901","card":"article","date":1262149201,"longURL":"https://www.bloomberg.com/news/articles/2009-12-30/fatal-flying-on-airlines-no-accident-in-pilot-complaints-to-faa"},{"title":"Pilot Complaints Highlight Hazards of Regional Airlines","id":"O1PG7P6JTSE801","card":"article","date":1262312820,"longURL":"https://www.bloomberg.com/news/articles/2009-12-31/pilot-complaints-highlight-hazards-of-regional-airlinesbusinessweek-business-news-stock-market-and-financial-advice"},{"title":"Emaar Chairman Leads Investor Group Buying Americana Stake","id":"O20D156TTDSE01","card":"article","date":1454587761,"longURL":"https://www.bloomberg.com/news/articles/2016-02-04/al-khair-signs-initial-accord-to-sell-americana-stake-to-adeptio"},{"title":"The Best Modern Takes on the Yuppie, Seventies-Era Cocktail Spot","id":"NRJ9DO6JIJUQ01","card":"article","date":1437058142,"longURL":"https://www.bloomberg.com/news/articles/2015-07-16/the-best-modern-takes-on-the-yuppie-seventies-era-cocktail-spot"},{"title":"Fast Food Menu Calorie Counter Should Be National Law.","id":"O1PDOE6KLVRA01","card":"article","date":1247803200,"longURL":"https://www.bloomberg.com/news/articles/2009-07-16/fast-food-menu-calorie-counter-should-be-national-law-dot"},{"title":"DeVry, E-Trade, Federal Signal, Merck: U.S. Equity Movers Final","id":"JV7ZOG07SXKY","card":"article","date":1201298272,"longURL":"https://www.bloomberg.com/news/articles/2008-01-25/devry-e-trade-federal-signal-merck-u-s-equity-movers-final"},{"title":"Santa Delivering Drones for Christmas Amid Rising Safety Concern","id":"NGMRPO6TTDT001","card":"article","date":1418838451,"longURL":"https://www.bloomberg.com/news/articles/2014-12-17/santa-delivering-drones-for-christmas-amid-rising-safety-concern"},{"title":"The Shine Is off Applebee's, Among Others","id":"O1P1L66JTSF201","card":"article","date":1218686400,"longURL":"https://www.bloomberg.com/news/articles/2008-08-13/the-shine-is-off-applebees-among-others"},{"title":"Buy Dress Barn to Profit From Small-Cap M&A Revival","id":"L6VTHF07SXKX01","card":"article","date":1281387957,"longURL":"https://www.bloomberg.com/news/articles/2010-08-09/dress-barn-among-top-small-cap-acquisition-candidates-credit-suisse-says"},{"title":"Red Farm Brings Pastrami Egg Rolls to West Village: Ryan Sutton","id":"LWM7DP1A1I4I01","card":"article","date":1325048460,"longURL":"https://www.bloomberg.com/news/articles/2011-12-28/red-farm-brings-pastrami-egg-rolls-to-west-village-ryan-sutton"},{"title":"TGI Solar to Buy Florida Waste-Gasification Projects From Eliho","id":"LVDZY26S972B01","card":"article","date":1322513699,"longURL":"https://www.bloomberg.com/news/articles/2011-11-28/tgi-solar-to-buy-florida-waste-gasification-projects-from-eliho"}]}