{"result":[{"name":"Key Statistics","table":[{"name":"Current P/E Ratio (ttm)","value":"22.82"},{"name":"Estimated P/E","value":"23.87","comment":"(2022-09)"},{"name":"Relative P/E","value":"1.12","comment":"vs IPSA:IND"},{"name":"Est. EPS","value":"6.14","comment":"(2022-09)"},{"name":"Est. PEG Ratio","value":"2.17"},{"name":"Market Cap (M)","value":"2,371,290.87"},{"name":"Shares Outstanding (M)","value":"16,185.18"},{"name":"Price/Book (mrq)","value":"33.83"},{"name":"Price/Sales (ttm)","value":"5.99"},{"name":"Dividend Indicated Gross Yield","value":"0.63%"},{"name":"Next Earnings Announcement","value":"2022-07-27"},{"name":"Last Dividend Reported","value":"0.23","comment":"(2022-05-06)"},{"name":"5Y Net Dividend Growth","value":"8.75%"},{"name":"Average Volume (30-day)","value":"210"}]}]}