{"quote":[{"securityType":"Common Stock","symbol":"RBLX","exchange":"New York","country":"United States","currency":"USD","resourceType":"Company","fundamentalDataCurrency":"USD","resourceSubtype":"Other","region":"AMERICAS","ticker":"rblx:us","tickerName":"RBLX:US","template":"Stock","tinyName":"ROBLOX Corp","name":"ROBLOX Corp","watchlist":true,"resourceId":"RBLX:US","id":"RBLX:US","title":"ROBLOX Corp","card":"security"},{"securityType":"Common Stock","symbol":"RBLX*","exchange":"BIVA","country":"United States","currency":"MXN","resourceType":"Company","fundamentalDataCurrency":"USD","resourceSubtype":"Other","region":"AMERICAS","ticker":"rblx*:mm","tickerName":"RBLX*:MM","template":"Stock","tinyName":"ROBLOX Corp","name":"ROBLOX Corp","watchlist":true,"resourceId":"RBLX*:MM","id":"RBLX*:MM","title":"ROBLOX Corp","card":"security"}],"news":[{"title":"Roblox’s Worst Post-Earnings Drop Wrecks Stock-Pop Narrative","id":"R7EH2BT0G1KW01","card":"article","date":1645045950,"longURL":"https://www.bloomberg.com/news/articles/2022-02-16/roblox-s-worst-post-earnings-plunge-wrecks-stock-pop-narrative"},{"title":"Roblox Direct Listing Reference Price Set by NYSE at $45","id":"QPPV2CDWLU6H01","card":"article","date":1615330086,"longURL":"https://www.bloomberg.com/news/articles/2021-03-09/roblox-direct-listing-reference-price-is-said-to-be-set-at-45"},{"title":"Roblox Reaches $46 Billion Valuation in Direct Listing Debut","id":"QPRHR0DWLU7101","card":"article","date":1615406831,"longURL":"https://www.bloomberg.com/news/articles/2021-03-10/roblox-reaches-44-billion-valuation-in-direct-listing-debut"},{"title":"David Baszucki, CEO Who Took Roblox (RBLX) Public: Bloomberg 50 2021","id":"R3FLAZDWLU6B01","card":"article","date":1638353051,"longURL":"https://www.bloomberg.com/news/features/2021-12-01/david-baszucki-ceo-who-took-roblox-rblx-public-bloomberg-50-2021"},{"title":"Video Game Platform Roblox Files for IPO Listing $1 Billion Goal","id":"QK2DYSDWLU6901","card":"article","date":1605827447,"longURL":"https://www.bloomberg.com/news/articles/2020-11-19/video-game-platform-roblox-files-for-ipo-listing-1-billion-goal"},{"title":"GameStop (GME), Roblox (RBLX), Greensill, Coal: Investments in the Spotlight","id":"QPV21ODWRGG001","card":"article","date":1615559964,"longURL":"https://www.bloomberg.com/news/articles/2021-03-12/gamestop-gme-roblox-rblx-greensill-coal-investments-in-the-spotlight"},{"title":"How MeganPlays Built a Multimillion-Dollar Roblox (RBLX) Gaming Empire","id":"QS87FJT1UM1201","card":"article","date":1619532703,"longURL":"https://www.bloomberg.com/news/articles/2021-04-27/how-meganplays-built-a-multimillion-dollar-roblox-rblx-gaming-empire"}]}