{"result":[{"name":"Key Statistics","table":[{"name":"Estimated P/E","value":"50.16","comment":"(2022-12)"},{"name":"Earnings Per Share (ttm)","value":"-0.36"},{"name":"Est. EPS","value":"0.37","comment":"(2022-12)"},{"name":"Market Cap (M)","value":"1,510.44"},{"name":"Shares Outstanding (M)","value":"68.04"},{"name":"Price/Book (mrq)","value":"19.67"},{"name":"Price/Sales (ttm)","value":"4.93"},{"name":"Next Earnings Announcement","value":"2022-08-18"},{"name":"Average Volume (30-day)","value":"360,043"}]}]}