{"result":[{"name":"Key Statistics","table":[{"name":"Current P/E Ratio (ttm)","value":"29.51"},{"name":"Estimated P/E","value":"27.97","comment":"(2022-06)"},{"name":"Relative P/E","value":"1.44","comment":"vs IPSA:IND"},{"name":"Est. EPS","value":"9.49","comment":"(2022-06)"},{"name":"Est. PEG Ratio","value":"2.17"},{"name":"Market Cap (M)","value":"1,985,458.93"},{"name":"Shares Outstanding (M)","value":"7,479.03"},{"name":"Price/Book (mrq)","value":"12.25"},{"name":"Price/Sales (ttm)","value":"10.41"},{"name":"Dividend Indicated Gross Yield","value":"0.93%"},{"name":"Next Earnings Announcement","value":"2022-07-27"},{"name":"Last Dividend Reported","value":"0.62","comment":"(2022-05-18)"},{"name":"5Y Net Dividend Growth","value":"9.60%"},{"name":"Average Volume (30-day)","value":"111"}]}]}