[{"id":"20220427cg38387","sourceId":"pr-newswire","sourceName":"PR Newswire","providerName":"PR Newswire","title":"Thinking about buying stock in Mattel, Zentalis Pharmaceuticals, Acutus Medical, Allogene Therapeutics, or NeoGenomics?","publishedDate":"2022-04-27T09:01:00-05:00"},{"id":"202204277763","sourceId":"dow-jones","sourceName":"Global News Select","providerName":"Dow Jones","title":"Zentalis Pharmaceuticals Sells Shares to Pfizer for $25 Million","publishedDate":"2022-04-27T06:39:00-05:00"},{"id":"202111174530","sourceId":"dow-jones","sourceName":"Global News Select","providerName":"Dow Jones","title":"Zentalis Gets FDA Fast-Track Designation for ZN-c3 in Uterine Serous Carcinoma","publishedDate":"2021-11-17T06:32:00-06:00"}]