[{"id":"8544116","sourceId":"globe-newswire","sourceName":"GlobeNewswire","providerName":"GlobeNewswire","title":"Tenable Integrates Terrascan Into Nessus to Enable Secure Cloud Application Delivery","publishedDate":"2022-05-17T08:00:00-05:00"},{"id":"8529335","sourceId":"globe-newswire","sourceName":"GlobeNewswire","providerName":"GlobeNewswire","title":"Tenable Ranked #1 for 2020 Market Share in Device Vulnerability Management for Third Consecutive Year by Leading Analyst Firm","publishedDate":"2022-04-27T08:00:00-05:00"},{"id":"8529449","sourceId":"globe-newswire","sourceName":"GlobeNewswire","providerName":"GlobeNewswire","title":"Tenable Announces First Quarter 2022 Financial Results","publishedDate":"2022-04-26T15:06:00-05:00"},{"id":"8529447","sourceId":"globe-newswire","sourceName":"GlobeNewswire","providerName":"GlobeNewswire","title":"Tenable Agrees to Acquire Bit Discovery","publishedDate":"2022-04-26T15:05:00-05:00"},{"id":"8524751","sourceId":"globe-newswire","sourceName":"GlobeNewswire","providerName":"GlobeNewswire","title":"Tenable Streamlines Workflows to Secure OT Operations with Enhanced ServiceNow Partnership","publishedDate":"2022-04-19T08:21:15-05:00"},{"id":"8520022","sourceId":"globe-newswire","sourceName":"GlobeNewswire","providerName":"GlobeNewswire","title":"Tenable Announces Date for its First Quarter 2022 Earnings Conference Call","publishedDate":"2022-04-12T08:00:00-05:00"},{"id":"20220223441","sourceId":"marketwatch","sourceName":"MarketWatch","providerName":"Dow Jones","title":"Russia-Ukraine conflict creates best time for these cybersecurity stocks in a decade","publishedDate":"2022-02-23T15:18:00-06:00"},{"id":"8489872","sourceId":"globe-newswire","sourceName":"GlobeNewswire","providerName":"GlobeNewswire","title":"Tenable Announces New Product Certification Program","publishedDate":"2022-02-23T08:00:00-06:00"},{"id":"20211005215","sourceId":"marketwatch","sourceName":"MarketWatch","providerName":"Dow Jones","title":"Analyst forecasts tech stock rebound of at least 10% and says rate fears will soon pass","publishedDate":"2021-10-05T09:06:00-05:00"}]